topsis/102203385.py
topsis/__init__.py
Topsis_Garima_102203385-1.0.1.dist-info/LICENSE
Topsis_Garima_102203385-1.0.1.dist-info/METADATA
Topsis_Garima_102203385-1.0.1.dist-info/WHEEL
Topsis_Garima_102203385-1.0.1.dist-info/entry_points.txt
Topsis_Garima_102203385-1.0.1.dist-info/top_level.txt
Topsis_Garima_102203385-1.0.1.dist-info/RECORD
