Metadata-Version: 2.2
Name: Topsis-Garima-102203385
Version: 1.0.1
Summary: Perform TOPSIS (Technique for Order Preference by Similarity to Ideal Solution) analysis on a dataset.
Home-page: https://github.com/garimaahuja112/Topsis-Garima-102203385
Author: Garima Ahuja
Author-email: garimaahuja217@gmail.com
License: MIT
Classifier: License :: OSI Approved :: MIT License
Classifier: Programming Language :: Python :: 3.6
Classifier: Programming Language :: Python :: 3.7
Classifier: Programming Language :: Python :: 3.8
Classifier: Programming Language :: Python :: 3.9
License-File: LICENSE
Requires-Dist: pandas
Requires-Dist: numpy
Dynamic: author
Dynamic: author-email
Dynamic: classifier
Dynamic: description
Dynamic: description-content-type
Dynamic: home-page
Dynamic: license
Dynamic: requires-dist
Dynamic: summary
